jupyterlab_commands_toolkit/__init__.py
jupyterlab_commands_toolkit/_version.py
jupyterlab_commands_toolkit/tools.py
jupyterlab_commands_toolkit/events/jupyterlab-command-result.yml
jupyterlab_commands_toolkit/events/jupyterlab-command.yml
jupyterlab_commands_toolkit-0.1.2.data/data/etc/jupyter/jupyter_server_config.d/jupyterlab_commands_toolkit.json
jupyterlab_commands_toolkit-0.1.2.data/data/share/jupyter/labextensions/jupyterlab-commands-toolkit/package.json
jupyterlab_commands_toolkit-0.1.2.data/data/share/jupyter/labextensions/jupyterlab-commands-toolkit/static/108.9024c7713209f701fdfa.js
jupyterlab_commands_toolkit-0.1.2.data/data/share/jupyter/labextensions/jupyterlab-commands-toolkit/static/509.66c305c55f8f81e7e6ff.js
jupyterlab_commands_toolkit-0.1.2.data/data/share/jupyter/labextensions/jupyterlab-commands-toolkit/static/728.a98366e3571837076f70.js
jupyterlab_commands_toolkit-0.1.2.data/data/share/jupyter/labextensions/jupyterlab-commands-toolkit/static/remoteEntry.aefeeb24d68dcb466431.js
jupyterlab_commands_toolkit-0.1.2.data/data/share/jupyter/labextensions/jupyterlab-commands-toolkit/static/style.js
jupyterlab_commands_toolkit-0.1.2.data/data/share/jupyter/labextensions/jupyterlab-commands-toolkit/static/third-party-licenses.json
jupyterlab_commands_toolkit-0.1.2.data/data/share/jupyter/labextensions/jupyterlab-commands-toolkit/install.json
jupyterlab_commands_toolkit-0.1.2.dist-info/METADATA
jupyterlab_commands_toolkit-0.1.2.dist-info/WHEEL
jupyterlab_commands_toolkit-0.1.2.dist-info/entry_points.txt
jupyterlab_commands_toolkit-0.1.2.dist-info/licenses/LICENSE
jupyterlab_commands_toolkit-0.1.2.dist-info/RECORD
