Metadata-Version: 2.4
Name: jupyterlab_commands_toolkit
Version: 0.1.2
Summary: A Jupyter extension that provides an AI toolkit for JupyterLab commands.
Project-URL: Homepage, https://github.com/jupyter-ai-contrib/jupyterlab-commands-toolkit
Project-URL: Bug Tracker, https://github.com/jupyter-ai-contrib/jupyterlab-commands-toolkit/issues
Project-URL: Repository, https://github.com/jupyter-ai-contrib/jupyterlab-commands-toolkit.git
Author-email: Project Jupyter Team <jupyter@googlegroups.com>
License: BSD 3-Clause License
License-File: LICENSE
Keywords: jupyter,jupyterlab,jupyterlab-extension
Classifier: Framework :: Jupyter
Classifier: Framework :: Jupyter :: JupyterLab
Classifier: Framework :: Jupyter :: JupyterLab :: 4
Classifier: Framework :: Jupyter :: JupyterLab :: Extensions
Classifier: Framework :: Jupyter :: JupyterLab :: Extensions :: Prebuilt
Classifier: License :: OSI Approved :: BSD License
Classifier: Programming Language :: Python
Classifier: Programming Language :: Python :: 3
Classifier: Programming Language :: Python :: 3.9
Classifier: Programming Language :: Python :: 3.10
Classifier: Programming Language :: Python :: 3.11
Classifier: Programming Language :: Python :: 3.12
Classifier: Programming Language :: Python :: 3.13
Requires-Python: >=3.9
Requires-Dist: jupyter-server<3,>=2.4.0
Requires-Dist: jupyterlab-eventlistener
Provides-Extra: mcp
Requires-Dist: jupyter-server-mcp>=0.1.2; extra == 'mcp'
